tensorflow_transform/__init__.py
tensorflow_transform/analyzer_nodes.py
tensorflow_transform/analyzers.py
tensorflow_transform/analyzers_test.py
tensorflow_transform/annotators.py
tensorflow_transform/annotators_test.py
tensorflow_transform/common.py
tensorflow_transform/common_test.py
tensorflow_transform/common_types.py
tensorflow_transform/gaussianization.py
tensorflow_transform/gaussianization_test.py
tensorflow_transform/graph_context.py
tensorflow_transform/graph_tools.py
tensorflow_transform/graph_tools_test.py
tensorflow_transform/impl_helper.py
tensorflow_transform/impl_helper_test.py
tensorflow_transform/info_theory.py
tensorflow_transform/info_theory_test.py
tensorflow_transform/inspect_preprocessing_fn.py
tensorflow_transform/inspect_preprocessing_fn_test.py
tensorflow_transform/keras_lib.py
tensorflow_transform/mappers.py
tensorflow_transform/mappers_test.py
tensorflow_transform/nodes.py
tensorflow_transform/nodes_test.py
tensorflow_transform/output_wrapper.py
tensorflow_transform/pickle_helper.py
tensorflow_transform/pretrained_models.py
tensorflow_transform/pretrained_models_test.py
tensorflow_transform/py.typed
tensorflow_transform/schema_inference.py
tensorflow_transform/schema_inference_test.py
tensorflow_transform/test_case.py
tensorflow_transform/test_case_test.py
tensorflow_transform/tf2_utils.py
tensorflow_transform/tf2_utils_test.py
tensorflow_transform/tf_utils.py
tensorflow_transform/tf_utils_test.py
tensorflow_transform/version.py
tensorflow_transform/beam/__init__.py
tensorflow_transform/beam/analysis_graph_builder.py
tensorflow_transform/beam/analysis_graph_builder_test.py
tensorflow_transform/beam/analyzer_cache.py
tensorflow_transform/beam/analyzer_cache_test.py
tensorflow_transform/beam/analyzer_impls.py
tensorflow_transform/beam/analyzer_impls_test.py
tensorflow_transform/beam/annotators_test.py
tensorflow_transform/beam/beam_nodes.py
tensorflow_transform/beam/bucketize_integration_test.py
tensorflow_transform-1.17.0.dist-info/licenses/LICENSE
tensorflow_transform-1.17.0.dist-info/METADATA
tensorflow_transform-1.17.0.dist-info/WHEEL
tensorflow_transform-1.17.0.dist-info/namespace_packages.txt
tensorflow_transform-1.17.0.dist-info/top_level.txt
tensorflow_transform-1.17.0.dist-info/RECORD
