Metadata-Version: 2.4
Name: tensorflow-transform
Version: 1.17.0
Summary: A library for data preprocessing with TensorFlow
Home-page: https://www.tensorflow.org/tfx/transform/get_started
Download-URL: https://github.com/tensorflow/transform/tags
Author: Google Inc.
Author-email: tensorflow-extended-dev@googlegroups.com
License: Apache 2.0
Keywords: tensorflow transform tfx
Classifier: Development Status :: 5 - Production/Stable
Classifier: Intended Audience :: Developers
Classifier: Intended Audience :: Education
Classifier: Intended Audience :: Science/Research
Classifier: License :: OSI Approved :: Apache Software License
Classifier: Operating System :: OS Independent
Classifier: Programming Language :: Python
Classifier: Programming Language :: Python :: 3
Classifier: Programming Language :: Python :: 3.9
Classifier: Programming Language :: Python :: 3.10
Classifier: Programming Language :: Python :: 3.11
Classifier: Programming Language :: Python :: 3 :: Only
Classifier: Topic :: Scientific/Engineering
Classifier: Topic :: Scientific/Engineering :: Artificial Intelligence
Classifier: Topic :: Scientific/Engineering :: Mathematics
Classifier: Topic :: Software Development
Classifier: Topic :: Software Development :: Libraries
Classifier: Topic :: Software Development :: Libraries :: Python Modules
Requires-Python: >=3.9,<4
License-File: LICENSE
Requires-Dist: absl-py<2.0.0,>=0.9
Requires-Dist: apache-beam[gcp]<3,>=2.53; python_version >= "3.11"
Requires-Dist: apache-beam[gcp]<2.51,>=2.50; python_version < "3.11"
Requires-Dist: numpy>=1.22.0
Requires-Dist: protobuf<6.0.0,>=4.25.2; python_version >= "3.11"
Requires-Dist: protobuf<6.0.0,>=4.21.6; python_version < "3.11"
Requires-Dist: pyarrow<11,>=10
Requires-Dist: pydot<2,>=1.2
Requires-Dist: tensorflow<2.18,>=2.17
Requires-Dist: tensorflow-metadata<1.18.0,>=1.17.1
Requires-Dist: tf_keras>=2
Requires-Dist: tfx-bsl<1.18.0,>=1.17.1
Dynamic: author
Dynamic: author-email
Dynamic: classifier
Dynamic: description
Dynamic: description-content-type
Dynamic: download-url
Dynamic: home-page
Dynamic: keywords
Dynamic: license
Dynamic: license-file
Dynamic: requires-dist
Dynamic: requires-python
Dynamic: summary
